postino/__init__.py
postino/address.py
postino/config.py
postino/constants.py
postino/construct.py
postino/postino.py
postino/send.py
postino/utils.py
postino-0.3.dist-info/DESCRIPTION.rst
postino-0.3.dist-info/METADATA
postino-0.3.dist-info/RECORD
postino-0.3.dist-info/WHEEL
postino-0.3.dist-info/metadata.json
postino-0.3.dist-info/top_level.txt
