Metadata-Version: 2.0
Name: postino
Version: 0.3
Summary: Easy email sending
Home-page: http://github.com/mlesniew/postino
Author: Michał Leśniewski
Author-email: mlesniew@gmail.com
License: GPLv3
Platform: UNKNOWN
